vcontrold/__init__.py
vcontrold/_vcontrold_config.py
vcontrold/vcontrold.py
pyvcontrold_net-2.0.0.dist-info/LICENSE.txt
pyvcontrold_net-2.0.0.dist-info/METADATA
pyvcontrold_net-2.0.0.dist-info/WHEEL
pyvcontrold_net-2.0.0.dist-info/top_level.txt
pyvcontrold_net-2.0.0.dist-info/RECORD
