Metadata-Version: 2.1
Name: pyvcontrold-net
Version: 2.0.0
Summary: A small library to interact with vcontrold (openv).
Home-page: https://github.com/tsvsj/pyvcontrold-net
Author: Sven Schaefer
Author-email: tsvsjoj@gamil.com
License: Apache-2.0
Project-URL: Bug Reports, https://github.com/tsvsj/pyvcontrold-net/issues
Project-URL: Donating, https://www.buymeacoffee.com/tsvsj
Project-URL: Say Thanks!, https://saythanks.io/to/tsvsj
Project-URL: Source, https://github.com/tsvsj/pyvcontrold-net
Keywords: smarthome,vcontrold,openv,viessmann,heating control
Platform: UNKNOWN
Classifier: Development Status :: 5 - Production/Stable
Classifier: Intended Audience :: Developers
Classifier: Programming Language :: Python :: 3
Classifier: Programming Language :: Python :: 3.6
Classifier: Programming Language :: Python :: 3.7
Classifier: Programming Language :: Python :: 3.8
Classifier: Programming Language :: Python :: 3.9
Classifier: License :: OSI Approved :: Apache Software License
Classifier: Natural Language :: German
Classifier: Natural Language :: English
Classifier: Operating System :: OS Independent
Classifier: Topic :: Home Automation
Classifier: Topic :: Software Development :: Libraries
Classifier: Topic :: Software Development :: Libraries :: Python Modules
Requires-Python: >=3.6, <4
License-File: LICENSE.txt
Requires-Dist: PyYAML
Requires-Dist: Jinja2
